litenv/__init__.py
litenv/_modidx.py
litenv/cmds.py
litenv/cons.py
litenv/dcls.py
litenv/rich.py
litenv-0.0.35.dist-info/LICENSE
litenv-0.0.35.dist-info/METADATA
litenv-0.0.35.dist-info/WHEEL
litenv-0.0.35.dist-info/entry_points.txt
litenv-0.0.35.dist-info/top_level.txt
litenv-0.0.35.dist-info/RECORD
