Metadata-Version: 2.1
Name: litenv
Version: 0.0.35
Summary: quickly make pytorch environments with mamba
Home-page: https://github.com/dsm-72/litenv
Author: dsm-72
Author-email: sumner.magruder@yale.edu
License: Apache Software License 2.0
Keywords: lit env litenv conda typer rich mamba environments mps accelator pytorch environments
Classifier: Development Status :: 4 - Beta
Classifier: Intended Audience :: Developers
Classifier: Natural Language :: English
Classifier: Programming Language :: Python :: 3.7
Classifier: Programming Language :: Python :: 3.8
Classifier: Programming Language :: Python :: 3.9
Classifier: Programming Language :: Python :: 3.10
Classifier: Programming Language :: Python :: 3.11
Classifier: License :: OSI Approved :: Apache Software License
Requires-Python: >=3.7
License-File: LICENSE
Requires-Dist: nchr
Requires-Dist: nlit
Requires-Dist: rich
Requires-Dist: typer
Requires-Dist: pyyaml
Requires-Dist: questionary
Requires-Dist: importlib-resources
Provides-Extra: dev
